BounceClassifier/__init__.py
BounceClassifier/bounce_classifier.py
Bounce_classifier/__init__.py
Bounce_classifier/bounce_classifier.py
BounceClassifier-0.3.3.dist-info/LICENSE
BounceClassifier-0.3.3.dist-info/METADATA
BounceClassifier-0.3.3.dist-info/WHEEL
BounceClassifier-0.3.3.dist-info/top_level.txt
BounceClassifier-0.3.3.dist-info/RECORD
